itk/Configuration/ITKConvolutionConfig.py
itk/Configuration/ITKConvolution_snake_case.py
itk/Configuration/ITKCurvatureFlowConfig.py
itk/Configuration/ITKCurvatureFlow_snake_case.py
itk/Configuration/ITKDisplacementFieldConfig.py
itk/Configuration/ITKDisplacementField_snake_case.py
itk/Configuration/ITKEigenConfig.py
itk/Configuration/ITKEigen_snake_case.py
itk/Configuration/ITKImageComposeConfig.py
itk/Configuration/ITKImageCompose_snake_case.py
itk/Configuration/ITKImageIntensityConfig.py
itk/Configuration/ITKImageIntensity_snake_case.py
itk/Configuration/ITKImageSourcesConfig.py
itk/Configuration/ITKImageSources_snake_case.py
itk/Configuration/ITKImageStatisticsConfig.py
itk/Configuration/ITKImageStatistics_snake_case.py
itk/Configuration/ITKOptimizersConfig.py
itk/Configuration/ITKOptimizers_snake_case.py
itk/Configuration/ITKPathConfig.py
itk/Configuration/ITKPath_snake_case.py
itk/Configuration/ITKSmoothingConfig.py
itk/Configuration/ITKSmoothing_snake_case.py
itk/Configuration/ITKSpatialObjectsConfig.py
itk/Configuration/ITKSpatialObjects_snake_case.py
itk/Configuration/ITKThresholdingConfig.py
itk/Configuration/ITKThresholding_snake_case.py
itk/ITKConvolutionPython.py
itk/ITKCostFunctionsPython.py
itk/ITKCurvatureFlowPython.py
itk/ITKDisplacementFieldPython.py
itk/ITKEigenPython.py
itk/ITKImageComposePython.py
itk/ITKImageIntensityPython.py
itk/ITKImageSourcesPython.py
itk/ITKImageStatisticsPython.py
itk/ITKOptimizersBasePython.py
itk/ITKOptimizersPython.py
itk/ITKPathPython.py
itk/ITKSmoothingPython.py
itk/ITKSpatialObjectsPython.py
itk/ITKThresholdingPython.py
itk/_ITKConvolutionPython.cpython-39-darwin.so
itk/_ITKCurvatureFlowPython.cpython-39-darwin.so
itk/_ITKDisplacementFieldPython.cpython-39-darwin.so
itk/_ITKEigenPython.cpython-39-darwin.so
itk/_ITKImageComposePython.cpython-39-darwin.so
itk/_ITKImageIntensityPython.cpython-39-darwin.so
itk/_ITKImageSourcesPython.cpython-39-darwin.so
itk/_ITKImageStatisticsPython.cpython-39-darwin.so
itk_numerics-5.4.4.post1.dist-info/METADATA
itk_numerics-5.4.4.post1.dist-info/WHEEL
itk_numerics-5.4.4.post1.dist-info/licenses/LICENSE
itk_numerics-5.4.4.post1.dist-info/licenses/ITK-source/ITK/LICENSE
itk_numerics-5.4.4.post1.dist-info/licenses/ITK-source/ITK/NOTICE
itk_numerics-5.4.4.post1.dist-info/RECORD
